{
  "title": "Han Han's Blog",
  "url": "https://blog.yucun.fun",
  "domain": "yucun.fun",
  "description": "Han Han's Blog",
  "genre": "blog",
  "googleAnalyticsId": "G-RRQ6ZF3KNM",
  "feed": {
    "subtitle": "blog",
    "filename": "feed.xml",
    "path": "/feed/feed.xml",
    "id": "https://update-me.com"
  },
  "jsonfeed": {
    "path": "/feed/feed.json",
    "url": "https://update-me.com/feed/feed.json"
  },
  "author": {
    "name": "Han Han",
    "twitterHandle": "update_me"
  },
  "publisher": {
    "name": "Han Han"
  }
}
